[
    {
        "nome": "LPQA",
        "andar": 1,
        "bloco": "BP",
        "responsavel": "Fabio Caetano",
        "horario": "8h - 21h, segunda à sexta",
        "descricao": "",
        "id": 0
    },
    {
        "nome": "LERCA",
        "horario": "7:30 - 17:00, segunda à sexta",
        "responsavel": "Andréa Cysne",
        "descricao": "Trabalho de pesquisas ambientais, energias renováveis e sustentabilidade.",
        "andar": 1,
        "bloco": "BP",
        "id": 1
    },
    {
        "nome": "LMG",
        "andar": 1,
        "bloco": "BP",
        "responsavel": "Marcos Porto",
        "horario": "7:30h - 17h, segunda à sexta",
        "descricao": "O Laboratório de Modelagem Geotécnica (LMG) tem como objetivo auxiliar as disciplinas de Geotecnia dos cursos de Engenharia Civil, Edificações, Estradas e Saneamento com o desenvolvimento de modelos numéricos, físicos e materiais de aula.",
        "id": 2
    },
    {
        "nome": "LMC",
        "andar": 1,
        "bloco": "BP",
        "responsavel": "Indisponível",
        "horario": "Indisponível",
        "descricao": "Indisponível",
        "id": 3
    },
    {
        "nome": "LIMAR",
        "andar": 1,
        "bloco": "BP",
        "responsavel": "Aline Carvalho de Oliveira",
        "descricao": "Análises fisico-químicas de águas residuárias, análises hidráulicas e tratamento de água.",
        "horario": "8:00 às 18:00",
        "id": 4
    },
    {
        "nome": "LAPADA",
        "andar": 2,
        "bloco": "BP",
        "responsavel": "Anaxa Goras, Mauro Oliveira e Reinaldo",
        "horario": "7:30h - 18:30h, segunda à sexta",
        "descricao": "Espaço para desenvolvimento/pesquisa para bolsistas",
        "id": 5
    },
    {
        "nome": "LIA",
        "andar": 2,
        "bloco": "BP",
        "responsavel": "Ajalmar",
        "horario": "7:30h - 20:00h, segunda à sexta",
        "descricao": "Desenvolvimento de projetos de inovação da EMBRAPII envolvendo back-end e front-end",
        "id": 6
    },
    {
        "nome": "LAPISCO",
        "andar": 2,
        "bloco": "BP",
        "responsavel": "Pedro Pedrosa",
        "horario": "7:30h - 20:00h, segunda à sexta",
        "descricao": "O Laboratório de Processamento de Imagens, Sinais e Computação (LAPISCO) concentra suas áreas de pesquisa principalmente em Processamento Digital de Imagens, Sinais e Computação Aplicada em diversas áreas envolvendo Inteligência Artificial e aprendizado de máquina.",
        "id": 7
    },
    {
        "nome": "LDS",
        "andar": 3,
        "bloco": "BP",
        "responsavel": "Antônio Barros Serra",
        "horario": "8h - 17h, segunda à sexta",
        "descricao": "Embarca Tech. Projeto de ensino voltado para sistemas embarcados.",
        "id": 8
    },
    {
        "nome": "GDESTE",
        "andar": 3,
        "bloco": "BP",
        "responsavel": "Jorge Frederickson, Carlos Maurício",
        "horario": "8h - 18h, segunda à sexta",
        "descricao": "Desenvolvimento de sistemas embarcados, desenvolvimento full-stack e modelagem e impressão 3D.",
        "id": 9
    },
    {
        "nome": "LPDS",
        "andar": 3,
        "bloco": "BP",
        "responsavel": "Auzir Ripardo",
        "horario": "7:30h - 22h, segunda à sexta",
        "descricao": "Pesquisa e desenvolvimento de sistemas embarcados voltados para fisioterapia",
        "id": 10
    },
    {
        "nome": "Fotônica",
        "andar": 3,
        "bloco": "BP",
        "responsavel": "Glendo de Freitas",
        "horario": "7:30h - 20h, segunda à sexta",
        "descricao": "Sensoriamento Óptico, desenvolvimento de sensores ópticos. Nano-estrutura nanofotônica, IA, comunicações ópticas, sistemas embarcados e química.",
        "id": 11
    },
    {
        "nome": "Apple Academy (Campfire)",
        "andar": 4,
        "bloco": "BP",
        "responsavel": "Carlos Hairon, Antônio Barros Serra",
        "horario": "8h - 18h, segunda à sexta",
        "descricao": "Laboratório Apple focado em desenvolvimento de aplicativos para os dispositivos Apple.",
        "id": 12
    },
    {
        "nome": "Apple Academy (Sandbox)",
        "andar": 5,
        "bloco": "BP",
        "responsavel": "Carlos Hairon, Antônio Barros Serra",
        "horario": "8h - 18h, segunda à sexta",
        "descricao": "Laboratório Apple focado em desenvolvimento de aplicativos para os dispositivos Apple.",
        "id": 13
    }
]
